wind_parser/__init__.py
wind_parser/parser.py
wind_parser/test_parser.py
wind_parser/utils.py
wind_parser-0.1.3.dist-info/METADATA
wind_parser-0.1.3.dist-info/LICENSE
wind_parser-0.1.3.dist-info/WHEEL
wind_parser-0.1.3.dist-info/RECORD
