Metadata-Version: 2.1
Name: wind-parser
Version: 0.1.3
Summary: Python wind parser is a parser used to retrieve arguments for command line interfaces and turn them into python dictionary
Home-page: https://github.com/anthonyraf/wind-parser
License: Apache-2.0
Keywords: cli,parser
Author: Anthony Rafidison
Author-email: benjaraf006@gmail.com
Requires-Python: >=3.8
Classifier: License :: OSI Approved :: Apache Software License
Classifier: Programming Language :: Python :: 3
Classifier: Programming Language :: Python :: 3.8
Classifier: Programming Language :: Python :: 3.9
Classifier: Programming Language :: Python :: 3.10
Classifier: Programming Language :: Python :: 3.11
Project-URL: Repository, https://github.com/anthonyraf/wind-parser
